DataMemory/data_memory.v
module data_memory (
    input         clk,
    input  [31:0] address,
    input  [31:0] data_in,
    input  [1:0]  write,   // 00: no write, 01: byte, 10: halfword, 11: word
    input  [1:0]  data,    // 00: byte, 01: halfword, 10: word
    output reg [31:0] data_out
);

    // 1K memory (1024 x 8-bit = 1024 bytes = 256 words)
    reg [7:0] mem [0:1023];

    wire [31:0] addr = address & 32'h000003FF; // Mask to fit in 1K

    always @(posedge clk) begin
        case (write)
            2'b01: mem[addr]     <= data_in[7:0];                    // Byte write
            2'b10: begin                                            // Halfword write
                mem[addr]     <= data_in[7:0];
                mem[addr + 1] <= data_in[15:8];
            end
            2'b11: begin                                            // Word write
                mem[addr]     <= data_in[7:0];
                mem[addr + 1] <= data_in[15:8];
                mem[addr + 2] <= data_in[23:16];
                mem[addr + 3] <= data_in[31:24];
            end
        endcase
    end

    always @(*) begin
        case (data)
            2'b00: data_out = {{24{mem[addr][7]}}, mem[addr]};                  // Sign-extended byte
            2'b01: data_out = {{16{mem[addr + 1][7]}}, mem[addr + 1], mem[addr]}; // Sign-extended halfword
            2'b10: data_out = {mem[addr + 3], mem[addr + 2], mem[addr + 1], mem[addr]}; // Full word
            default: data_out = 32'bx;
        endcase
    end

endmodule

BranchCompare/branch_compare.v
module branch_compare (
    input [31:0] reg1,
    input [31:0] reg2,
    input [2:0] funct3,       // Instruction[14:12]
    output reg branch_taken
);
    always @(*) begin
        case (funct3)
            3'b000: branch_taken = (reg1 == reg2);                     // BEQ
            3'b001: branch_taken = (reg1 != reg2);                     // BNE
            3'b100: branch_taken = ($signed(reg1) < $signed(reg2));   // BLT
            3'b101: branch_taken = ($signed(reg1) >= $signed(reg2));  // BGE
            3'b110: branch_taken = (reg1 < reg2);                     // BLTU
            3'b111: branch_taken = (reg1 >= reg2);                    // BGEU
            default: branch_taken = 1'b0;
        endcase
    end
endmodule

ALU/alu_m_extension.v
// Multiplication Extension for RISC-V M Extension (MUL, MULH, MULHSU, MULHU)
module alu_m_extension (
    input [31:0] data1,
    input [31:0] data2,
    input [4:0] alu_control,
    output reg [31:0] result
);

    // 64-bit multiplication results
    wire [63:0] mul_signed;         // For MUL and MULH
    wire [63:0] mul_signed_unsigned; // For MULHSU
    wire [63:0] mul_unsigned;       // For MULHU

    assign mul_signed          = $signed(data1) * $signed(data2);
    assign mul_signed_unsigned = $signed(data1) * $unsigned(data2);
    assign mul_unsigned        = $unsigned(data1) * $unsigned(data2);

    always @(*) begin
        case (alu_control)
            5'b01000: result = mul_signed[31:0];          // MUL: lower 32 bits of signed * signed
            5'b01001: result = mul_signed[63:32];         // MULH: upper 32 bits of signed * signed
            5'b01010: result = mul_unsigned[63:32];       // MULHU: upper 32 bits of unsigned * unsigned
            5'b01011: result = mul_signed_unsigned[63:32];// MULHSU: upper 32 bits of signed * unsigned
            default:  result = 32'b0;
        endcase
    end

endmodule

ALU/alu_core.v
module alu_core (
    input [31:0] data1,
    input [31:0] data2,
    input [4:0] alu_control,
    output reg [31:0] result
);
    always @(*) begin
        case (alu_control)
            5'b00000: result = data1 + data2;                                // ADD
            5'b00001: result = data1 - data2;                                // SUB
            5'b00010: result = data1 | data2;                                // OR
            5'b00011: result = data1 ^ data2;                                // XOR
            5'b00100: result = data1 & data2;                                // AND
            5'b00101: result = data1 >> data2;                               // SRL
            5'b00110: result = data1 << data2;                               // SLL
            5'b00111: result = $signed(data1) >>> data2;                    // SRA
            5'b10000: result = (data1 < data2) ? 32'b1 : 32'b0;              // SLT
            5'b10001: result = data2;                                       // Forwarding
            default:   result = 32'b0;
        endcase
    end
endmodule

ALUControlUnit/alu_control_unit.v
module alu_control_unit (
    input [1:0] alu_op,               // Comes from main control unit
    input [6:0] funct7,               // Instruction[31:25]
    input [2:0] funct3,               // Instruction[14:12]
    output reg [4:0] alu_control      // Output to ALU and M-extension
);

    always @(*) begin
        case (alu_op)
            2'b00: alu_control = 5'b00000; // Load/Store -> ADD
            2'b01: begin                   // Branch
                case (funct3)
                    3'b000: alu_control = 5'b00001; // BEQ -> SUB
                    3'b001: alu_control = 5'b00001; // BNE -> SUB
                    3'b100: alu_control = 5'b10000; // BLT -> SLT
                    3'b101: alu_control = 5'b10000; // BGE -> SLT
                    default: alu_control = 5'b00000;
                endcase
            end
            2'b10: begin                   // R-type or I-type
                case ({funct7, funct3})
                    10'b0000000_000: alu_control = 5'b00000; // ADD
                    10'b0100000_000: alu_control = 5'b00001; // SUB
                    10'b0000000_111: alu_control = 5'b00100; // AND
                    10'b0000000_110: alu_control = 5'b00010; // OR
                    10'b0000000_100: alu_control = 5'b00011; // XOR
                    10'b0000000_001: alu_control = 5'b00110; // SLL
                    10'b0000000_101: alu_control = 5'b00101; // SRL
                    10'b0100000_101: alu_control = 5'b00111; // SRA
                    10'b0000000_010: alu_control = 5'b10000; // SLT
                    10'b0000000_011: alu_control = 5'b10000; // SLTU
                    // M-extension
                    10'b0000001_000: alu_control = 5'b01000; // MUL
                    10'b0000001_001: alu_control = 5'b01001; // MULH
                    10'b0000001_010: alu_control = 5'b01010; // MULHU
                    10'b0000001_011: alu_control = 5'b01011; // MULHSU
                    10'b0000001_100: alu_control = 5'b01100; // DIV
                    10'b0000001_101: alu_control = 5'b01101; // DIVU
                    10'b0000001_110: alu_control = 5'b01110; // REM
                    10'b0000001_111: alu_control = 5'b01111; // REMU
                    default: alu_control = 5'b00000;
                endcase
            end
            default: alu_control = 5'b00000;
        endcase
    end
endmodule

ControlUnit/control_unit.v
module control_unit (
    input  [6:0] opcode,
    output reg       reg_write,
    output reg       mem_read,
    output reg       mem_write,
    output reg       mem_to_reg,
    output reg       alu_src,
    output reg       branch,
    output reg [1:0] alu_op
);

    always @(*) begin
        // Default values
        reg_write   = 0;
        mem_read    = 0;
        mem_write   = 0;
        mem_to_reg  = 0;
        alu_src     = 0;
        alu_op      = 2'b00;
        branch      = 0;

        case (opcode)
            7'b0110011: begin // R-type
                reg_write   = 1;
                alu_src     = 0;
                alu_op      = 2'b10;
            end
            7'b0010011: begin // I-type ALU (addi, andi, ori, etc.)
                reg_write   = 1;
                alu_src     = 1;
                alu_op      = 2'b11;
            end
            7'b0000011: begin // Load
                reg_write   = 1;
                mem_read    = 1;
                mem_to_reg  = 1;
                alu_src     = 1;
                alu_op      = 2'b00;
            end
            7'b0100011: begin // Store
                mem_write   = 1;
                alu_src     = 1;
                alu_op      = 2'b00;
            end
            7'b1100011: begin // Branch
                branch      = 1;
                alu_src     = 0;
                alu_op      = 2'b01;
            end
            default: begin
                // Unsupported or NOP
            end
        endcase
    end

endmodule

ImmGenerator/imm_generator.v
module imm_generator (
    input  [31:0] instr,
    output reg [31:0] imm_out
);

    wire [6:0] opcode = instr[6:0];

    always @(*) begin
        case (opcode)
            7'b0010011,  // I-type (addi, andi, ori, etc.)
            7'b0000011,  // I-type (load)
            7'b1100111:  // I-type (jalr)
                imm_out = {{20{instr[31]}}, instr[31:20]};  // sign-extend

            7'b0100011:  // S-type (store)
                imm_out = {{20{instr[31]}}, instr[31:25], instr[11:7]};

            7'b1100011:  // B-type (branch)
                imm_out = {{19{instr[31]}}, instr[31], instr[7], instr[30:25], instr[11:8], 1'b0};

            7'b0110111,  // U-type (LUI)
            7'b0010111:  // U-type (AUIPC)
                imm_out = {instr[31:12], 12'b0};

            7'b1101111:  // J-type (JAL)
                imm_out = {{11{instr[31]}}, instr[31], instr[19:12], instr[20], instr[30:21], 1'b0};

            default:
                imm_out = 32'b0;
        endcase
    end

endmodule

RegFile/register_file.v
module register_file (
    input         clk,
    input         we,             // Write enable
    input  [4:0]  rs1_addr,       // Read register 1 address
    input  [4:0]  rs2_addr,       // Read register 2 address
    input  [4:0]  rd_addr,        // Write register address
    input  [31:0] rd_data,        // Data to write
    output [31:0] rs1_data,       // Read data 1
    output [31:0] rs2_data        // Read data 2
);

    reg [31:0] regs [0:31];       // 32 registers of 32 bits

    // Read ports are combinational
    assign rs1_data = (rs1_addr == 5'd0) ? 32'd0 : regs[rs1_addr];
    assign rs2_data = (rs2_addr == 5'd0) ? 32'd0 : regs[rs2_addr];

    // Write port on rising clock edge
    always @(posedge clk) begin
        if (we && (rd_addr != 5'd0)) begin
            regs[rd_addr] <= rd_data;
        end
    end
endmodule

IMEM/instruction_memory.v
module instruction_memory (
    input  [31:0] addr,       // Byte address from PC
    output [31:0] instr       // 32-bit instruction
);

    // Memory size: 256 words (1 KB), can be adjusted
    reg [31:0] memory [0:255];

    // Initialize from file (optional)
    initial begin
        $readmemh("program.hex", memory);  // Load instructions in hex
    end

    assign instr = memory[addr[9:2]]; // Word aligned access (ignore lower 2 bits)

endmodule

PC/pc.v
module pc (
    input         clk,
    input         reset,
    input         pc_write,          // Control signal to allow PC update
    input  [31:0] next_pc,           // Next PC (e.g., PC+4 or branch target)
    output reg [31:0] pc_out         // Current PC
);

    always @(posedge clk or posedge reset) begin
        if (reset) begin
            pc_out <= 32'h00000000;  // Start at address 0
        end else if (pc_write) begin
            pc_out <= next_pc;
        end
    end
endmodule

CPU/cpu.v
`include ".//PC/pc.v"
`include ".//IMEM/instruction_memory.v"
`include ".//ImmGenerator/imm_generator.v"
`include ".//ControlUnit/control_unit.v"
`include ".//RegisterFile/register_file.v"
`include ".//ALUControlUnit/alu_control_unit.v"
`include ".//ALU/alu_core.v"
`include ".//ALU/alu_m_extension.v"
`include ".//BranchCompare/branch_compare.v"
`include ".//DataMemory/data_memory.v"
`timescale 1ns / 1ps

module cpu (
    input wire clk,
    input wire reset
);

// ----------- PC -----------
wire [31:0] PC;
wire [31:0] PC_next;

// Branch predictor result
wire [31:0] branch_target;
wire pc_src;

assign PC_next = pc_src ? branch_target : PC + 4;

pc pc (
    .clk(clk),
    .reset(reset),
    .pc_write(1'b1),
    .next_pc(PC_next),
    .pc_out(PC)
);

// ----------- IF Stage -----------
wire [31:0] instr;
instruction_memory imem (
    .addr(PC),
    .instr(instr)
);

// ----------- IF/ID Pipeline Register -----------
reg [31:0] IF_ID_PC, IF_ID_instr;

always @(posedge clk) begin
    IF_ID_PC <= PC;
    IF_ID_instr <= instr;
end

// ----------- ID Stage -----------
wire [4:0] rs1 = IF_ID_instr[19:15];
wire [4:0] rs2 = IF_ID_instr[24:20];
wire [4:0] rd  = IF_ID_instr[11:7];
wire [6:0] opcode = IF_ID_instr[6:0];
wire [2:0] funct3 = IF_ID_instr[14:12];
wire [6:0] funct7 = IF_ID_instr[31:25];

wire [31:0] rd1, rd2;
register_file rf (
    .clk(clk),
    .rs1_addr(rs1),
    .rs2_addr(rs2),
    .rd_addr(MEM_WB_rd),
    .rd_data(WB_result),
    .we(MEM_WB_reg_write),
    .rs1_data(rd1),
    .rs2_data(rd2)
);

wire [31:0] imm;
imm_generator imm_gen (
    .instr(IF_ID_instr),
    .imm_out(imm)
);

// Control Signals
wire reg_write, mem_read, mem_write, mem_to_reg, alu_src, branch;
wire [1:0] alu_op;
control_unit cu (
    .opcode(opcode),
    .reg_write(reg_write),
    .mem_read(mem_read),
    .mem_write(mem_write),
    .mem_to_reg(mem_to_reg),
    .alu_src(alu_src),
    .alu_op(alu_op),
    .branch(branch)
);

// ----------- ID/EX Pipeline Register -----------
reg [31:0] ID_EX_PC, ID_EX_imm, ID_EX_rd1, ID_EX_rd2;
reg [4:0] ID_EX_rd;
reg [2:0] ID_EX_funct3;
reg [6:0] ID_EX_funct7;
reg ID_EX_reg_write, ID_EX_mem_read, ID_EX_mem_write, ID_EX_mem_to_reg, ID_EX_alu_src, ID_EX_branch;
reg [1:0] ID_EX_alu_op;

always @(posedge clk) begin
    ID_EX_PC <= IF_ID_PC;
    ID_EX_rd1 <= rd1;
    ID_EX_rd2 <= rd2;
    ID_EX_imm <= imm;
    ID_EX_rd <= rd;
    ID_EX_funct3 <= funct3;
    ID_EX_funct7 <= funct7;
    ID_EX_reg_write <= reg_write;
    ID_EX_mem_read <= mem_read;
    ID_EX_mem_write <= mem_write;
    ID_EX_mem_to_reg <= mem_to_reg;
    ID_EX_alu_src <= alu_src;
    ID_EX_alu_op <= alu_op;
    ID_EX_branch <= branch;
end

// ----------- EX Stage -----------
wire [4:0] alu_control;

alu_control_unit alu_cu (
    .alu_op(ID_EX_alu_op),
    .funct3(ID_EX_funct3),
    .funct7(ID_EX_funct7),
    .alu_control(alu_control)
);

wire [31:0] alu_input_b = (ID_EX_alu_src) ? ID_EX_imm : ID_EX_rd2;

wire [31:0] alu_out_standard;
wire [31:0] alu_out_mext;

alu_core alu_core (
    .data1(ID_EX_rd1),
    .data2(alu_input_b),
    .alu_control(alu_control),
    .result(alu_out_standard)
);

alu_m_extension alu_mext_core (
    .data1(ID_EX_rd1),
    .data2(alu_input_b),
    .alu_control(alu_control),
    .result(alu_out_mext)
);

wire [31:0] alu_out = (alu_control[4:3] == 2'b01) ? alu_out_mext : alu_out_standard;

// ----------- Branch Comparator -----------
wire branch_taken;
branch_compare branch_cmp (
    .reg1(ID_EX_rd1),
    .reg2(ID_EX_rd2),
    .funct3(ID_EX_funct3),
    .branch_taken(branch_taken)
);

assign branch_target = ID_EX_PC + ID_EX_imm;
assign pc_src = ID_EX_branch && branch_taken;

// ----------- EX/MEM Pipeline Register -----------
reg [31:0] EX_MEM_alu_out, EX_MEM_rd2;
reg [4:0] EX_MEM_rd;
reg [2:0] EX_MEM_funct3;
reg EX_MEM_reg_write, EX_MEM_mem_read, EX_MEM_mem_write, EX_MEM_mem_to_reg;

always @(posedge clk) begin
    EX_MEM_alu_out <= alu_out;
    EX_MEM_rd2 <= ID_EX_rd2;
    EX_MEM_rd <= ID_EX_rd;
    EX_MEM_funct3 <= ID_EX_funct3;
    EX_MEM_reg_write <= ID_EX_reg_write;
    EX_MEM_mem_read <= ID_EX_mem_read;
    EX_MEM_mem_write <= ID_EX_mem_write;
    EX_MEM_mem_to_reg <= ID_EX_mem_to_reg;
end

// ----------- MEM Stage -----------
wire [1:0] mem_data_type = EX_MEM_funct3[1:0];
wire [1:0] mem_write_type = EX_MEM_mem_write ? EX_MEM_funct3[1:0] : 2'b00;
wire [31:0] mem_data_out;

data_memory dmem (
    .clk(clk),
    .address(EX_MEM_alu_out),
    .data_in(EX_MEM_rd2),
    .write(mem_write_type),
    .data(mem_data_type),
    .data_out(mem_data_out)
);

// ----------- MEM/WB Pipeline Register -----------
reg [31:0] MEM_WB_mem_data, MEM_WB_alu_out;
reg [4:0] MEM_WB_rd;
reg MEM_WB_reg_write, MEM_WB_mem_to_reg;

always @(posedge clk) begin
    MEM_WB_mem_data <= mem_data_out;
    MEM_WB_alu_out <= EX_MEM_alu_out;
    MEM_WB_rd <= EX_MEM_rd;
    MEM_WB_reg_write <= EX_MEM_reg_write;
    MEM_WB_mem_to_reg <= EX_MEM_mem_to_reg;
end

// ----------- WB Stage -----------
wire [31:0] WB_result = MEM_WB_mem_to_reg ? MEM_WB_mem_data : MEM_WB_alu_out;

endmodule

CPU/cpu_tb.v
// Simple testbench for riscv_cpu without hazards
`timescale 1ns / 1ps

module cpu_tb;
    reg clk;
    reg reset;

    // Instantiate the CPU
    cpu uut (
        .clk(clk),
        .reset(reset)
    );

    // Clock generation
    always #5 clk = ~clk; // 10ns clock period

    // Simulation control
    initial begin
        $dumpfile("cpu_tb.vcd");
        $dumpvars(0, cpu_tb);

        clk = 0;
        reset = 1;
        #20;
        reset = 0;

        // Run for a fixed number of cycles
        #200;
        $finish;
    end
endmodule

cpu_tb.vcd
$date
	Fri Jun 13 06:08:31 2025
$end
$version
	Icarus Verilog
$end
$timescale
	1ps
$end
$scope module cpu_tb $end
$var reg 1 ! clk $end
$var reg 1 " reset $end
$scope module uut $end
$var wire 1 ! clk $end
$var wire 1 # pc_src $end
$var wire 1 " reset $end
$var wire 5 $ rs2 [4:0] $end
$var wire 5 % rs1 [4:0] $end
$var wire 1 & reg_write $end
$var wire 32 ' rd2 [31:0] $end
$var wire 32 ( rd1 [31:0] $end
$var wire 5 ) rd [4:0] $end
$var wire 7 * opcode [6:0] $end
$var wire 2 + mem_write_type [1:0] $end
$var wire 1 , mem_write $end
$var wire 1 - mem_to_reg $end
$var wire 1 . mem_read $end
$var wire 2 / mem_data_type [1:0] $end
$var wire 32 0 mem_data_out [31:0] $end
$var wire 32 1 instr [31:0] $end
$var wire 32 2 imm [31:0] $end
$var wire 7 3 funct7 [6:0] $end
$var wire 3 4 funct3 [2:0] $end
$var wire 32 5 branch_target [31:0] $end
$var wire 1 6 branch_taken $end
$var wire 1 7 branch $end
$var wire 1 8 alu_src $end
$var wire 32 9 alu_out_standard [31:0] $end
$var wire 32 : alu_out_mext [31:0] $end
$var wire 32 ; alu_out [31:0] $end
$var wire 2 < alu_op [1:0] $end
$var wire 32 = alu_input_b [31:0] $end
$var wire 5 > alu_control [4:0] $end
$var wire 32 ? WB_result [31:0] $end
$var wire 32 @ PC_next [31:0] $end
$var wire 32 A PC [31:0] $end
$var reg 32 B EX_MEM_alu_out [31:0] $end
$var reg 3 C EX_MEM_funct3 [2:0] $end
$var reg 1 D EX_MEM_mem_read $end
$var reg 1 E EX_MEM_mem_to_reg $end
$var reg 1 F EX_MEM_mem_write $end
$var reg 5 G EX_MEM_rd [4:0] $end
$var reg 32 H EX_MEM_rd2 [31:0] $end
$var reg 1 I EX_MEM_reg_write $end
$var reg 32 J ID_EX_PC [31:0] $end
$var reg 2 K ID_EX_alu_op [1:0] $end
$var reg 1 L ID_EX_alu_src $end
$var reg 1 M ID_EX_branch $end
$var reg 3 N ID_EX_funct3 [2:0] $end
$var reg 7 O ID_EX_funct7 [6:0] $end
$var reg 32 P ID_EX_imm [31:0] $end
$var reg 1 Q ID_EX_mem_read $end
$var reg 1 R ID_EX_mem_to_reg $end
$var reg 1 S ID_EX_mem_write $end
$var reg 5 T ID_EX_rd [4:0] $end
$var reg 32 U ID_EX_rd1 [31:0] $end
$var reg 32 V ID_EX_rd2 [31:0] $end
$var reg 1 W ID_EX_reg_write $end
$var reg 32 X IF_ID_PC [31:0] $end
$var reg 32 Y IF_ID_instr [31:0] $end
$var reg 32 Z MEM_WB_alu_out [31:0] $end
$var reg 32 [ MEM_WB_mem_data [31:0] $end
$var reg 1 \ MEM_WB_mem_to_reg $end
$var reg 5 ] MEM_WB_rd [4:0] $end
$var reg 1 ^ MEM_WB_reg_write $end
$scope module alu_core $end
$var wire 32 _ data1 [31:0] $end
$var wire 32 ` data2 [31:0] $end
$var wire 5 a alu_control [4:0] $end
$var reg 32 b result [31:0] $end
$upscope $end
$scope module alu_cu $end
$var wire 2 c alu_op [1:0] $end
$var wire 3 d funct3 [2:0] $end
$var wire 7 e funct7 [6:0] $end
$var reg 5 f alu_control [4:0] $end
$upscope $end
$scope module alu_mext_core $end
$var wire 5 g alu_control [4:0] $end
$var wire 32 h data1 [31:0] $end
$var wire 32 i data2 [31:0] $end
$var wire 64 j mul_unsigned [63:0] $end
$var wire 64 k mul_signed_unsigned [63:0] $end
$var wire 64 l mul_signed [63:0] $end
$var reg 32 m result [31:0] $end
$upscope $end
$scope module branch_cmp $end
$var wire 3 n funct3 [2:0] $end
$var wire 32 o reg1 [31:0] $end
$var wire 32 p reg2 [31:0] $end
$var reg 1 6 branch_taken $end
$upscope $end
$scope module cu $end
$var wire 7 q opcode [6:0] $end
$var reg 2 r alu_op [1:0] $end
$var reg 1 8 alu_src $end
$var reg 1 7 branch $end
$var reg 1 . mem_read $end
$var reg 1 - mem_to_reg $end
$var reg 1 , mem_write $end
$var reg 1 & reg_write $end
$upscope $end
$scope module dmem $end
$var wire 32 s addr [31:0] $end
$var wire 32 t address [31:0] $end
$var wire 1 ! clk $end
$var wire 2 u data [1:0] $end
$var wire 32 v data_in [31:0] $end
$var wire 2 w write [1:0] $end
$var reg 32 x data_out [31:0] $end
$upscope $end
$scope module imem $end
$var wire 32 y instr [31:0] $end
$var wire 32 z addr [31:0] $end
$upscope $end
$scope module imm_gen $end
$var wire 32 { instr [31:0] $end
$var wire 7 | opcode [6:0] $end
$var reg 32 } imm_out [31:0] $end
$upscope $end
$scope module pc $end
$var wire 1 ! clk $end
$var wire 32 ~ next_pc [31:0] $end
$var wire 1 !" pc_write $end
$var wire 1 " reset $end
$var reg 32 "" pc_out [31:0] $end
$upscope $end
$scope module rf $end
$var wire 1 ! clk $end
$var wire 5 #" rd_addr [4:0] $end
$var wire 32 $" rd_data [31:0] $end
$var wire 5 %" rs1_addr [4:0] $end
$var wire 5 &" rs2_addr [4:0] $end
$var wire 1 ^ we $end
$var wire 32 '" rs2_data [31:0] $end
$var wire 32 (" rs1_data [31:0] $end
$upscope $end
$upscope $end
$upscope $end
$enddefinitions $end
$comment Show the parameter values. $end
$dumpall
$end
#0
$dumpvars
bx ("
bx '"
bx &"
bx %"
bx $"
bx #"
b0 ""
1!"
bx ~
bx }
bx |
bx {
b0 z
b1100000010000000100011 y
bx x
bx w
bx v
bx u
bx t
b0xxxxxxxxxx s
bx r
bx q
bx p
bx o
bx n
bx m
bx l
bx k
bx j
bx i
bx h
bx g
bx f
bx e
bx d
bx c
bx b
bx a
bx `
bx _
x^
bx ]
x\
bx [
bx Z
bx Y
bx X
xW
bx V
bx U
bx T
xS
xR
xQ
bx P
bx O
bx N
xM
xL
bx K
bx J
xI
bx H
bx G
xF
xE
xD
bx C
bx B
b0 A
bx @
bx ?
bx >
bx =
bx <
bx ;
bx :
bx 9
x8
x7
x6
bx 5
bx 4
bx 3
bx 2
b1100000010000000100011 1
bx 0
bx /
x.
x-
x,
bx +
bx *
bx )
bx (
bx '
x&
bx %
bx $
x#
1"
0!
$end
#5000
b0 (
b0 ("
07
b0 <
b0 r
18
0-
1,
0.
0&
b0 %
b0 %"
b11 $
b11 &"
b0 )
b100011 *
b100011 q
b10 4
b0 3
b0 2
b0 }
b100011 |
b1100000010000000100011 Y
b1100000010000000100011 {
b0 X
1!
#10000
0!
#15000
b0 ;
b0 :
b0 m
0#
b0 >
b0 a
b0 f
b0 g
b0 l
b0 k
b0 j
b0 =
b0 `
b0 i
b100 @
b100 ~
b0 9
b0 b
06
0M
b0 K
b0 c
1L
0R
1S
0Q
0W
b0 O
b0 e
b10 N
b10 d
b10 n
b0 T
b0 5
b0 P
b0 U
b0 _
b0 h
b0 o
b0 J
1!
#20000
0!
0"
#25000
b10 +
b10 w
b10 /
b10 u
b0 s
b10001010000011 1
b10001010000011 y
b1000 @
b1000 ~
0E
1F
0D
0I
b10 C
b0 G
b0 B
b0 t
b100 A
b100 z
b100 ""
1!
#30000
0!
#35000
b0 '
b0 '"
1-
1.
1&
18
0,
b0 ?
b0 $"
b0 $
b0 &"
b101 )
b11 *
b11 q
b11 |
b10011 1
b10011 y
b1100 @
b1100 ~
0\
0^
b0 ]
b0 #"
b0 Z
b10001010000011 Y
b10001010000011 {
b100 X
b1000 A
b1000 z
b1000 ""
1!
#40000
0!
#45000
b11 <
b11 r
18
0-
0.
1&
b0 )
b10011 *
b10011 q
b0 4
b10011 |
b10000 @
b10000 ~
b10011 Y
b10011 {
b1000 X
1R
0S
1Q
1W
b101 T
b0 V
b0 p
b100 5
b100 J
b1100 A
b1100 z
b1100 ""
1!
#50000
0!
#55000
b0 +
b0 w
16
b11000000000001010010011 1
b11000000000001010010011 y
b10100 @
b10100 ~
1E
0F
1D
1I
b101 G
b0 H
b0 v
b11 K
b11 c
0R
0Q
b0 N
b0 d
b0 n
b0 T
b1000 5
b1000 J
b1100 X
b10000 A
b10000 z
b10000 ""
1!
#60000
0!
#65000
bx '
bx '"
b110 $
b110 &"
b101 )
b110 2
b110 }
b0 /
b0 u
bx ?
bx $"
b1100000000001100010011 1
b1100000000001100010011 y
b11000 @
b11000 ~
b11000000000001010010011 Y
b11000000000001010010011 {
b10000 X
b1100 5
b1100 J
0E
0D
b0 C
b0 G
1\
1^
b101 ]
b101 #"
b10100 A
b10100 z
b10100 ""
1!
#70000
0!
#75000
b110 ;
b110 9
b110 b
b0 ?
b0 $"
b110 =
b110 `
b110 i
x6
b11 $
b11 &"
b110 )
b11 2
b11 }
b1000000011000101011001110110011 1
b1000000011000101011001110110011 y
b11100 @
b11100 ~
0\
b0 ]
b0 #"
b101 T
b110 P
bx V
bx p
b10110 5
b10000 J
b1100000000001100010011 Y
b1100000000001100010011 {
b10100 X
b11000 A
b11000 z
b11000 ""
1!
#80000
0!
#85000
b11 ;
bx (
bx ("
b10 <
b10 r
08
1&
b11 9
b11 b
b101 %
b101 %"
b110 $
b110 &"
b111 )
b110011 *
b110011 q
b11 4
b100000 3
b0 2
b0 }
b110011 |
b11 =
b11 `
b11 i
b110 s
b1000000011000101100001110110011 1
b1000000011000101100001110110011 y
b100000 @
b100000 ~
b1000000011000101011001110110011 Y
b1000000011000101011001110110011 {
b11000 X
b110 T
b11 P
b10111 5
b10100 J
b101 G
bx H
bx v
b110 B
b110 t
b11100 A
b11100 z
b11100 ""
1!
#90000
0!
#95000
bx ;
b110 ?
b110 $"
b11 s
bx =
bx `
bx i
bx 9
bx b
06
b100 4
b10011 1
b10011 y
b100100 @
b100100 ~
b101 ]
b101 #"
b110 Z
b110 G
b11 B
b11 t
b10 K
b10 c
0L
b100000 O
b100000 e
b11 N
b11 d
b11 n
b111 T
b0 P
bx l
bx k
bx j
bx U
bx _
bx h
bx o
b11000 5
b11000 J
b1000000011000101100001110110011 Y
b1000000011000101100001110110011 {
b11100 X
b100000 A
b100000 z
b100000 ""
1!
#100000
0!
#105000
b0 '
b0 '"
18
b11 <
b11 r
1&
b0 (
b0 ("
b0 %
b0 %"
b0 $
b0 &"
b0 )
b10011 *
b10011 q
b0 4
b0 3
b10011 |
x6
b11 /
b11 u
b0xxxxxxxxxx s
b11 ?
b11 $"
b101000 @
b101000 ~
b10011 Y
b10011 {
b100000 X
b100 N
b100 d
b100 n
b11100 5
b11100 J
b11 C
b111 G
bx B
bx t
b110 ]
b110 #"
b11 Z
b100100 A
b100100 z
b100100 ""
1!
#110000
0!
#115000
b0 ;
b0 9
b0 b
bx ?
bx $"
b0 /
b0 u
b0 l
b0 k
b0 j
b0 =
b0 `
b0 i
16
b101100000000001010010011 1
b101100000000001010010011 y
b101100 @
b101100 ~
b111 ]
b111 #"
bx Z
b100 C
b11 K
b11 c
1L
b0 O
b0 e
b0 N
b0 d
b0 n
b0 T
b0 V
b0 p
b0 U
b0 _
b0 h
b0 o
b100000 5
b100000 J
b100100 X
b101000 A
b101000 z
b101000 ""
1!
#120000
0!
#125000
bx '
bx '"
b1011 $
b1011 &"
b101 )
b1011 2
b1011 }
b0 s
b11100000000001100010011 1
b11100000000001100010011 y
b110000 @
b110000 ~
b101100000000001010010011 Y
b101100000000001010010011 {
b101000 X
b100100 5
b100100 J
b0 C
b0 G
b0 H
b0 v
b0 B
b0 t
b101100 A
b101100 z
b101100 ""
1!
#130000
0!
#135000
b1011 ;
b1011 9
b1011 b
b0 ?
b0 $"
b1011 =
b1011 `
b1011 i
x6
b111 $
b111 &"
b110 )
b111 2
b111 }
b10110000101011001110110011 1
b10110000101011001110110011 y
b110100 @
b110100 ~
b0 ]
b0 #"
b0 Z
b101 T
b1011 P
bx V
bx p
b110011 5
b101000 J
b11100000000001100010011 Y
b11100000000001100010011 {
b101100 X
b110000 A
b110000 z
b110000 ""
1!
#140000
0!
#145000
b111 ;
b110 (
b110 ("
b10 <
b10 r
08
1&
b111 9
b111 b
b101 %
b101 %"
b1100 $
b1100 &"
b111 )
b110011 *
b110011 q
b11 4
b1 3
b0 2
b0 }
b110011 |
b111 =
b111 `
b111 i
b1011 s
b10110000101100001110110011 1
b10110000101100001110110011 y
b111000 @
b111000 ~
b10110000101011001110110011 Y
b10110000101011001110110011 {
b110000 X
b110 T
b111 P
b110011 5
b101100 J
b101 G
bx H
bx v
b1011 B
b1011 t
b110100 A
b110100 z
b110100 ""
1!
#150000
0!
#155000
bx :
bx m
bx ;
b1011 ?
b1011 $"
b111 s
b1011 >
b1011 a
b1011 f
b1011 g
bx =
bx `
bx i
b0 9
b0 b
06
b100 4
b10110000101101001110110011 1
b10110000101101001110110011 y
b111100 @
b111100 ~
b101 ]
b101 #"
b1011 Z
b110 G
b111 B
b111 t
b10 K
b10 c
0L
b1 O
b1 e
b11 N
b11 d
b11 n
b111 T
b0 P
bx l
bx k
bx j
b110 U
b110 _
b110 h
b110 o
b110000 5
b110000 J
b10110000101100001110110011 Y
b10110000101100001110110011 {
b110100 X
b111000 A
b111000 z
b111000 ""
1!
#160000
0!
#165000
b0 ;
b0 :
b0 m
b1011 (
b1011 ("
b101 4
b1100 >
b1100 a
b1100 f
b1100 g
x6
b11 /
b11 u
b0xxxxxxxxxx s
b111 ?
b111 $"
bx 1
bx y
b1000000 @
b1000000 ~
b10110000101101001110110011 Y
b10110000101101001110110011 {
b111000 X
b100 N
b100 d
b100 n
b110100 5
b110100 J
b11 C
b111 G
bx B
bx t
b110 ]
b110 #"
b111 Z
b111100 A
b111100 z
b111100 ""
1!
#170000
0!
#175000
bx (
bx ("
b0 <
b0 r
0&
bx ?
bx $"
b0 /
b0 u
b0 s
b1101 >
b1101 a
b1101 f
b1101 g
bx %
bx %"
bx $
bx &"
bx )
bx *
bx q
bx 4
bx 3
bx |
b1000100 @
b1000100 ~
b111 ]
b111 #"
bx Z
b100 C
b0 B
b0 t
b101 N
b101 d
b101 n
b1011 U
b1011 _
b1011 h
b1011 o
b111000 5
b111000 J
bx Y
bx {
b111100 X
b1000000 A
b1000000 z
b1000000 ""
1!
#180000
0!
