Data Memory/data_memory.v
module DataMemory (
    input         clk,
    input  [31:0] address,
    input  [31:0] data_in,
    input  [1:0]  write,   // 00: no write, 01: byte, 10: halfword, 11: word
    input  [1:0]  data,    // 00: byte, 01: halfword, 10: word
    output reg [31:0] data_out
);

    // 1K memory (1024 x 8-bit = 1024 bytes = 256 words)
    reg [7:0] mem [0:1023];

    wire [31:0] addr = address & 32'h000003FF; // Mask to fit in 1K

    always @(posedge clk) begin
        case (write)
            2'b01: mem[addr]     <= data_in[7:0];                    // Byte write
            2'b10: begin                                            // Halfword write
                mem[addr]     <= data_in[7:0];
                mem[addr + 1] <= data_in[15:8];
            end
            2'b11: begin                                            // Word write
                mem[addr]     <= data_in[7:0];
                mem[addr + 1] <= data_in[15:8];
                mem[addr + 2] <= data_in[23:16];
                mem[addr + 3] <= data_in[31:24];
            end
        endcase
    end

    always @(*) begin
        case (data)
            2'b00: data_out = {{24{mem[addr][7]}}, mem[addr]};                  // Sign-extended byte
            2'b01: data_out = {{16{mem[addr + 1][7]}}, mem[addr + 1], mem[addr]}; // Sign-extended halfword
            2'b10: data_out = {mem[addr + 3], mem[addr + 2], mem[addr + 1], mem[addr]}; // Full word
            default: data_out = 32'b0;
        endcase
    end

endmodule

DataMemory/data_memory_tb.v
`timescale 1ns/1ps

module data_memory_tb;

    // Inputs
    reg clk;
    reg [31:0] address;
    reg [31:0] data_in;
    reg [1:0] write;
    reg [1:0] data;

    // Output
    wire [31:0] data_out;

    // Instantiate the module
    DataMemory uut (
        .clk(clk),
        .address(address),
        .data_in(data_in),
        .write(write),
        .data(data),
        .data_out(data_out)
    );

    // Clock generation
    initial begin
        clk = 0;
        forever #5 clk = ~clk;  // 10ns clock period
    end

    // Test sequence
    initial begin
        $dumpfile("data_memory_tb.vcd");
        $dumpvars(0, data_memory_tb);

        // Initialize all signals
        address = 0;
        data_in = 0;
        write = 2'b00;
        data = 2'b00;

        #10;

        // Write byte
        address = 32'h00000004;
        data_in = 32'h000000AA;
        write = 2'b01;
        #10 write = 2'b00; // Disable write

        // Read byte
        data = 2'b00;
        #10;

        // Write halfword
        address = 32'h00000008;
        data_in = 32'h0000BEEF;
        write = 2'b10;
        #10 write = 2'b00;

        // Read halfword
        data = 2'b01;
        #10;

        // Write word
        address = 32'h0000000C;
        data_in = 32'hDEADBEEF;
        write = 2'b11;
        #10 write = 2'b00;

        // Read word
        data = 2'b10;
        #10;

        $finish;
    end

endmodule

DataMemory/data_memory_tb.vcd
$date
	Thu Jun 12 23:46:41 2025
$end
$version
	Icarus Verilog
$end
$timescale
	1ps
$end
$scope module data_memory_tb $end
$var wire 32 ! data_out [31:0] $end
$var reg 32 " address [31:0] $end
$var reg 1 # clk $end
$var reg 2 $ data [1:0] $end
$var reg 32 % data_in [31:0] $end
$var reg 2 & write [1:0] $end
$scope module uut $end
$var wire 32 ' addr [31:0] $end
$var wire 32 ( address [31:0] $end
$var wire 1 # clk $end
$var wire 2 ) data [1:0] $end
$var wire 32 * data_in [31:0] $end
$var wire 2 + write [1:0] $end
$var reg 32 , data_out [31:0] $end
$upscope $end
$upscope $end
$enddefinitions $end
$comment Show the parameter values. $end
$dumpall
$end
#0
$dumpvars
bx ,
b0 +
b0 *
b0 )
b0 (
b0 '
b0 &
b0 %
b0 $
0#
b0 "
bx !
$end
#5000
1#
#10000
b100 '
0#
b1 &
b1 +
b10101010 %
b10101010 *
b100 "
b100 (
#15000
b11111111111111111111111110101010 !
b11111111111111111111111110101010 ,
1#
#20000
0#
b0 &
b0 +
#25000
1#
#30000
bx !
bx ,
b1000 '
0#
b10 &
b10 +
b1011111011101111 %
b1011111011101111 *
b1000 "
b1000 (
#35000
b11111111111111111111111111101111 !
b11111111111111111111111111101111 ,
1#
#40000
b11111111111111111011111011101111 !
b11111111111111111011111011101111 ,
0#
b1 $
b1 )
b0 &
b0 +
#45000
1#
#50000
bx !
bx ,
b1100 '
0#
b11 &
b11 +
b11011110101011011011111011101111 %
b11011110101011011011111011101111 *
b1100 "
b1100 (
#55000
b11111111111111111011111011101111 !
b11111111111111111011111011101111 ,
1#
#60000
b11011110101011011011111011101111 !
b11011110101011011011111011101111 ,
0#
b10 $
b10 )
b0 &
b0 +
